cpi/__init__.py
cpi/cli.py
cpi/cpi.db
cpi/defaults.py
cpi/download.py
cpi/errors.py
cpi/models.py
cpi/parsers.py
cpi-2.0.9.dist-info/licenses/LICENSE
cpi-2.0.9.dist-info/METADATA
cpi-2.0.9.dist-info/WHEEL
cpi-2.0.9.dist-info/entry_points.txt
cpi-2.0.9.dist-info/top_level.txt
cpi-2.0.9.dist-info/RECORD
